tredis/__init__.py
tredis/client.py
tredis/cluster.py
tredis/common.py
tredis/compat.py
tredis/connection.py
tredis/crc16.py
tredis/exceptions.py
tredis/geo.py
tredis/hashes.py
tredis/hyperloglog.py
tredis/keys.py
tredis/lists.py
tredis/pubsub.py
tredis/scripting.py
tredis/server.py
tredis/sets.py
tredis/sortedsets.py
tredis/strings.py
tredis/transactions.py
tredis-0.8.0.dist-info/METADATA
tredis-0.8.0.dist-info/RECORD
tredis-0.8.0.dist-info/WHEEL
tredis-0.8.0.dist-info/top_level.txt
